nmapthon2/__init__.py
nmapthon2/async_.py
nmapthon2/elements.py
nmapthon2/engine.py
nmapthon2/exceptions.py
nmapthon2/parser.py
nmapthon2/ports.py
nmapthon2/results.py
nmapthon2/scanner.py
nmapthon2/status.py
nmapthon2/utils.py
nmapthon2-0.1.5.dist-info/LICENSE
nmapthon2-0.1.5.dist-info/METADATA
nmapthon2-0.1.5.dist-info/WHEEL
nmapthon2-0.1.5.dist-info/top_level.txt
nmapthon2-0.1.5.dist-info/RECORD
