Metadata-Version: 2.1
Name: nmapthon2
Version: 0.1.5
Summary: The evolution of nmapthon, an Nmap automation library for humans.
Home-page: https://github.com/cblopez/nmapthon2
Author: cblopez
Author-email: cbarrallopez@gmail.com
License: Apache-2.0
Keywords: python,python3,nmap,module,scan,nse,port,service,async,network
Platform: UNKNOWN
Classifier: Development Status :: 4 - Beta
Classifier: Programming Language :: Python :: 3 :: Only
Classifier: Topic :: System :: Networking
Classifier: Topic :: Software Development :: Libraries :: Python Modules
Classifier: License :: OSI Approved :: Apache Software License
